witnet_lib/__init__.py
witnet_lib/logger.py
witnet_lib/map_nodes.py
witnet_lib/rpc_handler.py
witnet_lib/tcp_handler.py
witnet_lib/utils.py
witnet_lib/witnet_client.py
witnet_lib/proto_lib/__init__.py
witnet_lib/proto_lib/witnet_msg.py
witnet_lib/proto_lib/witnet_pb2.py
witnet_lib-1.0.0.dist-info/LICENSE
witnet_lib-1.0.0.dist-info/METADATA
witnet_lib-1.0.0.dist-info/WHEEL
witnet_lib-1.0.0.dist-info/top_level.txt
witnet_lib-1.0.0.dist-info/RECORD
