Metadata-Version: 2.1
Name: witnet-lib
Version: 1.0.0
Summary: Lightclient implementation library for witnet node
Home-page: https://github.com/harsh-98/witnet_lib
Author: harsh
Author-email: harshjniitr@gmail.com
License: MIT
Keywords: witnet blockchain lightclient proto
Platform: UNKNOWN
Classifier: Development Status :: 3 - Alpha
Classifier: Programming Language :: Python :: 3.4
Classifier: Programming Language :: Python :: 3.5
Classifier: Programming Language :: Python :: 3.6
Classifier: Programming Language :: Python :: 3.7
Classifier: License :: OSI Approved :: MIT License
Requires-Dist: google (==2.0.3)
Requires-Dist: protobuf (==3.12.2)
